{
    "basics": {
        "name": "Dmitry Verhoturov",
        "label": "Site Reliability Engineer",
        "picture": "https://www.gravatar.com/avatar/8b2d47d99e6af64b89e6a0721e3485eb?s=200",
        "email": "paskal.07@gmail.com",
        "phone": "+79166127441",
        "birth": {
            "date": "1991-03-24"
        },
        "website": "https://terrty.net",
        "summary": "<ul><li>8+ years of system engineering expertise and work with Linux servers.</li><li>3 years of management.</li><li>Excellent communication skills.</li><li>Solid UNIX and TCP/IP network fundamentals knowledge.</li><li>Huge expertise in monitoring.</li><li>Advanced troubleshooting and analytical skills.</li><li>Well-developed understanding of internet technologies and client/server architecture.</li></ul>",
        "location": {
            "address": "",
            "postalCode": "",
            "city": "Moscow",
            "countryCode": "RU",
            "region": ""
        },
        "profiles": [
            {
                "network": "StackOverflow",
                "username": "Dmitry Verhoturov",
                "url": "http://stackexchange.com/users/931242/dmitry-verkhoturov?tab=accounts"
            },
            {
                "network": "LinkedIn",
                "username": "Dmitry Verhoturov",
                "url": "https://www.linkedin.com/in/verhoturov/"
            }
        ]
    },
    "work": [
        {
            "company": "IPonWeb",
            "position": "Monitoring Team Lead",
            "website": "http://www.iponweb.com/",
            "startDate": "2015-02-01",
            "summary": "IPonWeb (300+ employees) provides technology to advertising industry, Real Time Bidding auctions in particular — company handles millions of transactions every minute, terabytes of data stored and processed every day. I created and managed a team of engineers, ensuring company services operations 24/7/365.",
            "location": {
                "city": "Moscow",
                "countryCode": "RU"
            },
            "highlights": [
                "Developed applications/modules in Python, Puppet (+Ruby) and SQL.",
                "Deployed and maintained applications on Amazon and Google cloud services.",
                "Part of my work is to implement changes, and I know well how to make other people do what I need. I interact with literally every team in the company in progress of introducing improvements.",
                "Created and integrated on-duty incident management procedures (how, when and what to do when you're on-call), by which duty shifts are operating since then.",
                "Created a new team of eight people in three cities from scratch.",
                "Wrote of a ton of documentation and recorder couple of videos for internal education.",
                "Halfway through team transformation to SRE."
            ]
        },
        {
            "company": "Svyaznoy Zagruzka",
            "position": "Sr. System Engineer",
            "website": "https://zagruzka.com/",
            "startDate": "2014-01-01",
            "endDate": "2015-02-01",
            "summary": "Svyaznoy Zagruzka (~40 employees) is a telecommunication content provider, it powers services which send and receive SMS messages and USSD requests, and gives that ability to hundreds of partners. I handled client integration and support. My day-to-day activity was monitoring and troubleshooting (network and application levels, Wireshark and SQL console were my best friends).",
            "location": {
                "city": "Moscow",
                "countryCode": "RU"
            },
            "highlights": [
                "Maintained and monitored the company’s software, self-written parts is Java, served by Glassfish and Tomcat — I've tuned these systems and debugged Java software.",
                "Created Python+Flask web application for recurring task of extracting network dump slices cut by time and client.",
                "Rewrote dozen of scripts to Python from Perl and Bash, and created a bunch of new ones.",
                "Maintained and tuned the IT infrastructure of the company. Every day I was working with Linux (CentOS, Debian), SQL (MySQL, MSSQL) and virtualization (VMware).",
                "I was the one detecting if problem is on our or client's side, and the one finding ways to fix problems on client's side no matter if they are tech-savvy or not. Also it was my responsibility to interact with other company technical departments, troubleshooting and fixing problems with external services providers."
            ]
        },
        {
            "company": "Russian Federation Army",
            "position": "Compulsory military service",
            "website": "http://eng.mil.ru",
            "startDate": "2012-12-01",
            "endDate": "2013-12-01",
            "summary": "Served army for one year after obtaining my degree.",
            "location": {
                "countryCode": "RU"
            }
        },
        {
            "company": "BioChemMack (medical equipment dealer)",
            "position": "System Engineer",
            "website": "http://www.biochemmack.ru/en/",
            "startDate": "2010-10-01",
            "endDate": "2012-12-01",
            "summary": "70 employees company, BioChemMack resells medical equipment. Initially, I was working on medical devices technical support. Then I shifted into internal services support.",
            "location": "Moscow",
            "highlights": [
                "Created and populated a wiki with information about internal infrastructure.",
                "Working as support facing clients, I have read tens of books of documentation and was being able to fix all different kinds of problems with software and hardware (for example used for the analysis of DNA).",
                "Migrated server from the old CentOS to Ubuntu, reviewed and rewrote configuration of all used Linux services and networking.",
                "Developed autonomous work of local network parts in case of events, such as a breakage of the main channel of communication or interrupted local connectivity."
            ]
        },
        {
            "company": "FS Group (metal reseller)",
            "position": "System Engineer",
            "website": "http://www.favor-group.ru/",
            "startDate": "2009-04-01",
            "endDate": "2010-10-01",
            "summary": "FS Group is a distributed reseller company with 10 employees in 3 different locations, my job was local system engineer. I was one-man army providing every IT service company needed.",
            "location": {
                "city": "Moscow",
                "countryCode": "RU"
            },
            "highlights": [
                "Established a network setup that is still in use in three original offices without changes.",
                "Created a documentation on company infrastructure for future engineers use.",
                "As a side job took a part in site development, SEO and advertising."
            ]
        }
    ],
    "education": [
        {
            "institution": "Moscow Financial-Industrial Academy",
            "area": "Informational security",
            "studyType": "Master's degree",
            "startDate": "2006-01-01",
            "endDate": "2012-01-01",
            "gpa": "",
            "location": {
                "city": "Moscow",
                "countryCode": "RU"
            },
            "website": "http://synergy.ru/",
            "courses": []
        }
    ],
    "awards": [],
    "publications": [],
    "skills": [
        {
            "name": "Cloud providers",
            "keywords": [
                "Amazon Web SERVICES",
                "Google Cloud Platform"
            ]
        },
        {
            "name": "Databases",
            "keywords": [
                "MySQL",
                "MongoDB",
                "Structured Query Language"
            ]
        },
        {
            "name": "Monitoring",
            "keywords": [
                "SRE principles",
                "Analysis and troubleshooting",
                "Establishing procedures",
                "Zabbix",
                "Prometheus"
            ]
        },
        {
            "name": "System administration",
            "keywords": [
                "Linux core utils",
                "Debian and Red Hat distributions family",
                "Puppet",
                "Docker",
                "Kubernetes"
            ]
        },
        {
            "name": "Programming",
            "keywords": [
                "Python",
                "Go",
                "Bash",
                "Ruby",
                "Perl"
            ]
        },
        {
            "name": "High load",
            "keywords": [
                "Site Reliability Engineering",
                "Load Balancing",
                "Scalable systems",
                "Cost-effective redundancy",
                "Automated provisioning"
            ]
        },
        {
            "name": "Continuous Delivery",
            "keywords": [
                "Jenkins",
                "Fabric",
                "Glassfish",
                "Tomcat",
                "Open Build Service"
            ]
        }
    ],
    "languages": [
        {
            "language": "English",
            "fluency": "Fluent"
        },
        {
            "language": "Russian",
            "fluency": "Native speaker"
        },
        {
            "language": "Spanish",
            "fluency": "Elementary"
        }
    ],
    "interests": [
        {
            "name": "Skydiving"
        }
    ]
}
